Metadata-Version: 2.1
Name: lagrang-pack
Version: 1.1
Summary: Lagrang product
Author: Svetlana Ilina
Author-email: skammm.04@mail.ru
License: MIT License
Requires-Python: >=3.5
License-File: LICENSE
